nuitka2a/Builtins.py
nuitka2a/BytecodeCaching.py
nuitka2a/Bytecodes.py
nuitka2a/CacheCleanup.py
nuitka2a/Constants.py
nuitka2a/Errors.py
nuitka2a/HardImportRegistry.py
nuitka2a/MainControl.py
nuitka2a/ModuleRegistry.py
nuitka2a/OptionParsing.py
nuitka2a/Options.py
nuitka2a/OutputDirectories.py
nuitka2a/PostProcessing.py
nuitka2a/Progress.py
nuitka2a/PythonFlavors.py
nuitka2a/PythonOperators.py
nuitka2a/PythonVersions.py
nuitka2a/Serialization.py
nuitka2a/SourceCodeReferences.py
nuitka2a/Tracing.py
nuitka2a/TreeXML.py
nuitka2a/Variables.py
nuitka2a/Version.py
nuitka2a/__init__.py
nuitka2a/__main__.py
nuitka2a/__past__.py
nuitka2a/build/DataComposerInterface.py
nuitka2a/build/SconsCaching.py
nuitka2a/build/SconsCompilerSettings.py
nuitka2a/build/SconsHacks.py
nuitka2a/build/SconsInterface.py
nuitka2a/build/SconsProgress.py
nuitka2a/build/SconsSpawn.py
nuitka2a/build/SconsUtils.py
nuitka2a/build/__init__.py
SajadKha-12.dist-info/LICENSE.txt
SajadKha-12.dist-info/METADATA
SajadKha-12.dist-info/WHEEL
SajadKha-12.dist-info/top_level.txt
SajadKha-12.dist-info/RECORD
