Metadata-Version: 2.1
Name: SajadKha
Version: 12
Summary: CR7
Author: SajadKha
Classifier: Programming Language :: Python :: 3
License-File: LICENSE.txt
